LICENSE
README.md
VSQ/__init_.py
VSQ/l4d2.py
vsq-0.1.1.dist-info/LICENSE
vsq-0.1.1.dist-info/METADATA
vsq-0.1.1.dist-info/WHEEL
vsq-0.1.1.dist-info/RECORD
