Metadata-Version: 2.1
Name: vsq
Version: 0.1.1
Summary: VALVE-Server Queries(now for L4D2)
Home-page: https://github.com/Umamusume-Agnes-Digital/VSQ
License: GPLv3
Keywords: steam,game,l4d2,query
Author: Agnes_Digital
Author-email: Z735803792@163.com
Requires-Python: >=3.7,<4.0
Classifier: License :: OSI Approved :: GNU General Public License v3 (GPLv3)
Classifier: License :: Other/Proprietary License
Classifier: Operating System :: OS Independent
Classifier: Programming Language :: Python
Classifier: Programming Language :: Python :: 3
Classifier: Programming Language :: Python :: 3.7
Classifier: Programming Language :: Python :: 3.8
Classifier: Programming Language :: Python :: 3.9
Classifier: Programming Language :: Python :: 3.10
Classifier: Programming Language :: Python :: 3.11
Classifier: Programming Language :: Python :: 3
Classifier: Programming Language :: Python :: 3.10
Classifier: Programming Language :: Python :: 3.8
Classifier: Programming Language :: Python :: 3.9
Project-URL: Repository, https://github.com/Umamusume-Agnes-Digital/VSQ
